{
  "id": "loadout_1",
  "name": "Deck",
  "cardIds": [
    "burn|Black",
    "courageous|White",
    "courageous|Red",
    "bulwark|Black",
    "dowse_with_holy_water|White",
    "dowse_with_holy_water|Red",
    "dowse_with_holy_water|Black",
    "narrow_gate|White",
    "tempest|Red",
    "sacrifice|Black",
    "seize|White",
    "seize|Red",
    "seize|Black",
    "stab|White",
    "stab|Red",
    "stab|Black",
    "strike|White",
    "strike|Red",
    "strike|Black",
    "stun|White",
    "stun|Red",
    "stun|Black",
    "vindicate|White",
    "vindicate|Red",
    "vindicate|Black",
    "divine_protection|White",
    "heavens_glory|Black",
    "divine_protection|Red",
    "divine_protection|Black",
    "heavens_glory|White"
  ],
  "weaponId": "hammer",
  "temperanceId": "radiance",
  "chestId": "pierced_heart_plate",
  "legsId": "lightning_grieves",
  "armsId": "purging_bracers",
  "headId": "focus_visor",
  "medalIds": [
    "st_michael",
    "st_luke"
  ]
}